promoai/__init__.py
promoai/main.py
promoai/aipa/__init__.py
promoai/aipa/abstraction.py
promoai/aipa/bpmn_analyzer.py
promoai/aipa/conversation.py
promoai/aipa/prompting.py
promoai/general_utils/__init__.py
promoai/general_utils/ai_providers.py
promoai/general_utils/app_utils.py
promoai/general_utils/constants.py
promoai/general_utils/llm_connection.py
promoai/model_generation/__init__.py
promoai/model_generation/code_extraction.py
promoai/model_generation/generator.py
promoai/model_generation/llm_model_generator.py
promoai/model_generation/model_generation.py
promoai/model_generation/validation.py
promoai/pn_to_powl/__init__.py
promoai/pn_to_powl/converter.py
promoai/pn_to_powl/converter_utils/__init__.py
promoai/pn_to_powl/converter_utils/cut_detection.py
promoai/pn_to_powl/converter_utils/powl_to_code.py
promoai/pn_to_powl/converter_utils/preprocessing.py
promoai/pn_to_powl/converter_utils/subnet_creation.py
promoai/pn_to_powl/converter_utils/weak_reachability.py
promoai/prompting/__init__.py
promoai/prompting/prompt_engineering.py
promoai/prompting/self_evaluation.py
promoai/prompting/shots.py
promoai-1.4.6.dist-info/licenses/LICENSE.txt
promoai-1.4.6.dist-info/METADATA
promoai-1.4.6.dist-info/WHEEL
promoai-1.4.6.dist-info/top_level.txt
promoai-1.4.6.dist-info/RECORD
