Metadata-Version: 2.4
Name: promoai
Version: 1.4.6
Summary: ProMoAI: Process Modeling with Generative AI
Author-email: Humam Kourani <humam.kourani@fit.fraunhofer.de>
License:                     GNU AFFERO GENERAL PUBLIC LICENSE
Project-URL: Repository, https://github.com/humam-kourani/ProMoAI
Keywords: process modeling,business process management,generative AI
Classifier: Development Status :: 4 - Beta
Classifier: Intended Audience :: Developers
Classifier: License :: OSI Approved :: GNU Affero General Public License v3 or later (AGPLv3+)
Classifier: Programming Language :: Python :: 3.9
Classifier: Programming Language :: Python :: 3.10
Requires-Python: >=3.9
License-File: LICENSE.txt
Requires-Dist: powl>=2.1.2
Requires-Dist: pm4py
Requires-Dist: setuptools
Requires-Dist: streamlit
Requires-Dist: requests
Requires-Dist: google-genai
Requires-Dist: anthropic
Requires-Dist: rustxes
Requires-Dist: cohere
Dynamic: license-file
